hca_util/__init__.py
hca_util/__main__.py
hca_util/aws_client.py
hca_util/bucket_policy.py
hca_util/common.py
hca_util/file_transfer.py
hca_util/hca_cmd.py
hca_util/local_state.py
hca_util/settings.py
hca_util/user_profile.py
hca_util/command/__init__.py
hca_util/command/area.py
hca_util/command/config.py
hca_util/command/create.py
hca_util/command/delete.py
hca_util/command/download.py
hca_util/command/list.py
hca_util/command/select.py
hca_util/command/upload.py
covid_util-0.0.8.dist-info/LICENSE
covid_util-0.0.8.dist-info/METADATA
covid_util-0.0.8.dist-info/WHEEL
covid_util-0.0.8.dist-info/entry_points.txt
covid_util-0.0.8.dist-info/top_level.txt
covid_util-0.0.8.dist-info/RECORD
