Metadata-Version: 2.1
Name: covid-util
Version: 0.0.8
Summary: CLI tool for uploading data to the European COVID-19 data platform backed up by Embassy S3
Home-page: https://github.com/EBIBioSamples/hca-util
Author: biosamples-dev
Author-email: biosamples-dev@ebi.ac.uk
License: Apache License
Platform: MacOS X
Platform: Posix
Classifier: License :: OSI Approved :: Apache Software License
Classifier: Operating System :: MacOS :: MacOS X
Classifier: Operating System :: POSIX
Classifier: Programming Language :: Python :: 3
Classifier: Programming Language :: Python :: 3.6
Classifier: Programming Language :: Python :: 3.7
Requires-Dist: boto3 (==1.12.*)
Requires-Dist: botocore (==1.15.*)
